beat/__init__.py
beat/__main__.py
beat/base_model.py
beat/cli.py
beat/conductivities.py
beat/ecg.py
beat/geometry.py
beat/monodomain_model.py
beat/monodomain_solver.py
beat/odesolver.py
beat/postprocess.py
beat/single_cell.py
beat/stimulation.py
beat/units.py
beat/utils.py
fenicsx_beat-0.2.3.dist-info/licenses/LICENSE
fenicsx_beat-0.2.3.dist-info/METADATA
fenicsx_beat-0.2.3.dist-info/WHEEL
fenicsx_beat-0.2.3.dist-info/entry_points.txt
fenicsx_beat-0.2.3.dist-info/top_level.txt
fenicsx_beat-0.2.3.dist-info/RECORD
