Metadata-Version: 2.4
Name: fenicsx-beat
Version: 0.2.3
Summary: Library to run cardiac EP simulations
Author-email: Henrik Finsberg <henriknf@simula.no>
License: MIT
Project-URL: Homepage, https://finsberg.github.io/fenicsx-beat
Project-URL: Documentation, https://finsberg.github.io/fenicsx-beat
Project-URL: Source, https://github.com/finsberg/fenicsx-beat
Project-URL: Tracker, https://github.com/finsberg/fenicsx-beat/issues
Keywords: cardiac,electrophysiology
Requires-Python: >=3.8
License-File: LICENSE
Requires-Dist: numpy
Requires-Dist: scipy
Requires-Dist: scifem>=0.2.14
Requires-Dist: pint
Requires-Dist: rich
Requires-Dist: fenics-dolfinx
Provides-Extra: test
Requires-Dist: pytest; extra == "test"
Requires-Dist: pytest-cov; extra == "test"
Provides-Extra: dev
Requires-Dist: pre-commit; extra == "dev"
Provides-Extra: pypi
Requires-Dist: twine; extra == "pypi"
Requires-Dist: build; extra == "pypi"
Provides-Extra: demos
Requires-Dist: cardiac-geometriesx; extra == "demos"
Requires-Dist: fenicsx-ldrb; extra == "demos"
Requires-Dist: gotranx; extra == "demos"
Requires-Dist: ukb-atlas; extra == "demos"
Provides-Extra: docs
Requires-Dist: jupyter-book; extra == "docs"
Requires-Dist: jupytext; extra == "docs"
Requires-Dist: fenicsx-beat[demos]; extra == "docs"
Requires-Dist: ipywidgets; extra == "docs"
Requires-Dist: imageio; extra == "docs"
Requires-Dist: pyvista[jupyter]; extra == "docs"
Provides-Extra: all
Requires-Dist: fenicsx-beat[test]; extra == "all"
Requires-Dist: fenicsx-beat[docs]; extra == "all"
Requires-Dist: fenicsx-beat[pypi]; extra == "all"
Requires-Dist: fenicsx-beat[dev]; extra == "all"
Requires-Dist: fenicsx-beat[demos]; extra == "all"
Provides-Extra: testpaths
Requires-Dist: tests; extra == "testpaths"
Dynamic: license-file
